mxnet_coreml_converter-0.1.0a7.data/purelib/converter/__init__.py
mxnet_coreml_converter-0.1.0a7.data/purelib/converter/_add_pooling.py
mxnet_coreml_converter-0.1.0a7.data/purelib/converter/_layers.py
mxnet_coreml_converter-0.1.0a7.data/purelib/converter/_mxnet_converter.py
mxnet_coreml_converter-0.1.0a7.data/purelib/converter/utils.py
mxnet_coreml_converter-0.1.0a7.data/scripts/mxnet_coreml_converter.py
mxnet_coreml_converter-0.1.0a7.dist-info/DESCRIPTION.rst
mxnet_coreml_converter-0.1.0a7.dist-info/METADATA
mxnet_coreml_converter-0.1.0a7.dist-info/RECORD
mxnet_coreml_converter-0.1.0a7.dist-info/WHEEL
mxnet_coreml_converter-0.1.0a7.dist-info/metadata.json
mxnet_coreml_converter-0.1.0a7.dist-info/top_level.txt
